GeometryLibPy/__init__.py
GeometryLibPy/geometry.py
geometryLibPy-1.0.0.dist-info/METADATA
geometryLibPy-1.0.0.dist-info/WHEEL
geometryLibPy-1.0.0.dist-info/top_level.txt
geometryLibPy-1.0.0.dist-info/RECORD
