Metadata-Version: 2.1
Name: geometryLibPy
Version: 1.0.0
Summary: This is the simplest module for calculating the area of a geometric figures.
Home-page: https://github.com/mav735/GeometryLibPy
Author: mav735
Author-email: mav735@ya.ru
Project-URL: GitHub, https://github.com/mav735/GeometryLibPy
Keywords: math geometry figures area
Classifier: Programming Language :: Python :: 3.12
Classifier: License :: OSI Approved :: MIT License
Classifier: Operating System :: OS Independent
Requires-Python: >=3.8
